setup.py
SDST/__init__.py
SDST/delly.py
SDST/demultiplexer.py
SDST/fastq.py
SDST/maf.py
SDST/main.py
SDST/mutect.py
SDST/seqvcf.py
SDST/snpeff.py
SDST/strelka.py
SDST/utils.py
SDST/varscan.py
SDST.egg-info/PKG-INFO
SDST.egg-info/SOURCES.txt
SDST.egg-info/dependency_links.txt
SDST.egg-info/entry_points.txt
SDST.egg-info/not-zip-safe
SDST.egg-info/requires.txt
SDST.egg-info/top_level.txt
SDST/commands/__init__.py
SDST/commands/strucvar.py
SDST/commands/utils.py
SDST/commands/varscan.py
SDST/commands/vcfCommands.py
SDST/strucvar/__init__.py
SDST/strucvar/crest.py
scripts/fastqc_contaminants_to_fasta.py
scripts/gasv2bedpe.py
scripts/runBreakdancer.py
scripts/runCrestParallel.py
scripts/seqtool
scripts/vcfSV2bed.py
scripts/vcfSampleRename.py