Metadata-Version: 1.0
Name: SDST
Version: 0.9.10
Summary: Useful routines to perform NGS data analysis tasks
Home-page: https://github.com/seandavi/SDST
Author: Sean Davis
Author-email: seandavi@gmail.com
License: MIT
Platform: UNKNOWN
